signal_ICT_DevarshBhatt_92400133073/__init__.py
signal_ICT_DevarshBhatt_92400133073/operations.py
signal_ICT_DevarshBhatt_92400133073/trigonometric_signals.py
signal_ICT_DevarshBhatt_92400133073/unitary_signals.py
signal_ict_devarshbhatt_92400133073-2.0.0.dist-info/licenses/LICENSE
signal_ict_devarshbhatt_92400133073-2.0.0.dist-info/METADATA
signal_ict_devarshbhatt_92400133073-2.0.0.dist-info/WHEEL
signal_ict_devarshbhatt_92400133073-2.0.0.dist-info/top_level.txt
signal_ict_devarshbhatt_92400133073-2.0.0.dist-info/RECORD
