Metadata-Version: 2.4
Name: signal_ICT_DevarshBhatt_92400133073
Version: 2.0.0
Summary: Python package for signal generation and operations
Author: DEVARSH BHATT
Author-email: devarsh.bhatt128171@marwadiuniversity.ac.in
License: MIT
Classifier: Programming Language :: Python :: 3
Classifier: License :: OSI Approved :: MIT License
Classifier: Operating System :: OS Independent
Requires-Python: >=3.6
License-File: LICENSE
Requires-Dist: numpy
Requires-Dist: matplotlib
Dynamic: author
Dynamic: author-email
Dynamic: classifier
Dynamic: description
Dynamic: description-content-type
Dynamic: license
Dynamic: license-file
Dynamic: requires-dist
Dynamic: requires-python
Dynamic: summary
